synonym_dict/__init__.py
synonym_dict/lower_dict.py
synonym_dict/synonym_dict.py
synonym_dict/synonym_set.py
synonym_dict/compartments/__init__.py
synonym_dict/compartments/compartment.py
synonym_dict/compartments/compartment_manager.py
synonym_dict/compartments/test_compartments.py
synonym_dict/example_compartments/__init__.py
synonym_dict/example_compartments/compartment.py
synonym_dict/example_compartments/compartment_manager.py
synonym_dict/example_compartments/test_compartments.py
synonym_dict/example_flowables/__init__.py
synonym_dict/example_flowables/cas_number.py
synonym_dict/example_flowables/flowable.py
synonym_dict/example_flowables/flowables.py
synonym_dict/example_flowables/test_cas_number.py
synonym_dict/example_flowables/test_flowables.py
synonym_dict/flowables/__init__.py
synonym_dict/flowables/cas_number.py
synonym_dict/flowables/flowable.py
synonym_dict/flowables/flowables.py
synonym_dict/flowables/test_cas_number.py
synonym_dict/flowables/test_flowables.py
synonym_dict/tests/__init__.py
synonym_dict/tests/test_lower_dict.py
synonym_dict/tests/test_synonym_dict.py
synonym_dict/tests/test_synonym_set.py
synonym_dict-0.2.5.dist-info/LICENSE
synonym_dict-0.2.5.dist-info/METADATA
synonym_dict-0.2.5.dist-info/WHEEL
synonym_dict-0.2.5.dist-info/top_level.txt
synonym_dict-0.2.5.dist-info/RECORD
