Metadata-Version: 2.1
Name: synonym_dict
Version: 0.2.5
Summary: A class that allows retrieval of a given object by any of its synonyms
Home-page: https://github.com/bkuczenski/synonym_dict
Author: Brandon Kuczenski
Author-email: bkuczenski@ucsb.edu
License: BSD 3-clause
Classifier: Development Status :: 4 - Beta
Classifier: Intended Audience :: End Users/Desktop
Classifier: Intended Audience :: Developers
Classifier: Intended Audience :: Science/Research
Classifier: License :: OSI Approved :: BSD License
Classifier: Natural Language :: English
Classifier: Operating System :: MacOS :: MacOS X
Classifier: Operating System :: Microsoft :: Windows
Classifier: Operating System :: POSIX
Classifier: Programming Language :: Python
Classifier: Programming Language :: Python :: 3
Classifier: Topic :: Scientific/Engineering :: Information Analysis
License-File: LICENSE
